{
    "1000207-011": [
        [
            "2016-01-03",
            1
        ]
    ],
    "1000405-014": [
        [
            "2016-04-10",
            1
        ]
    ],
    "1000405-018": [
        [
            "2016-05-03",
            1
        ]
    ],
    "1000501-002": [
        [
            "2016-02-04",
            1
        ]
    ],
    "1000501-016": [
        [
            "2016-01-22",
            1
        ]
    ],
    "1000505-015": [
        [
            "2016-02-14",
            1
        ]
    ],
    "1000513-001": [
        [
            "2016-02-13",
            1
        ],
        [
            "2016-02-15",
            1
        ]
    ],
    "1000705-004": [
        [
            "2016-05-25",
            1
        ]
    ],
    "1000705-012": [
        [
            "2016-06-01",
            1
        ]
    ],
    "1000721-011": [
        [
            "2016-05-18",
            1
        ]
    ],
    "1000802-020": [
        [
            "2016-04-22",
            1
        ]
    ],
    "1000802-029": [
        [
            "2016-01-12",
            1
        ]
    ],
    "1000804-014": [
        [
            "2016-06-25",
            1
        ]
    ],
    "1000807-010": [
        [
            "2016-06-05",
            1
        ]
    ],
    "1000901": [
        [
            "2016-04-20",
            1
        ]
    ],
    "1000905-014": [
        [
            "2016-01-25",
            1
        ]
    ],
    "1000911-018": [
        [
            "2016-02-03",
            1
        ]
    ],
    "1000913-009": [
        [
            "2016-05-15",
            1
        ]
    ],
    "1001003-005": [
        [
            "2016-07-06",
            1
        ]
    ],
    "1001301-026": [
        [
            "2016-01-11",
            1
        ],
        [
            "2016-01-15",
            1
        ],
        [
            "2016-01-16",
            2
        ],
        [
            "2016-01-30",
            1
        ]
    ],
    "1001301-030": [
        [
            "2016-01-11",
            1
        ]
    ],
    "1001301-053": [
        [
            "2016-01-18",
            1
        ]
    ],
    "1001301-059": [
        [
            "2016-01-25",
            1
        ]
    ],
    "1001301-060": [
        [
            "2016-01-13",
            1
        ],
        [
            "2016-01-22",
            1
        ],
        [
            "2016-01-25",
            1
        ],
        [
            "2016-01-29",
            1
        ]
    ],
    "1001301-073": [
        [
            "2016-01-13",
            1
        ]
    ],
    "1001301-078": [
        [
            "2016-06-26",
            1
        ]
    ],
    "1001302-005": [
        [
            "2016-01-01",
            1
        ],
        [
            "2016-05-17",
            1
        ]
    ],
    "1001303-007": [
        [
            "2016-06-16",
            1
        ]
    ],
    "1001303-016": [
        [
            "2016-01-05",
            1
        ]
    ],
    "1001306-010": [
        [
            "2016-01-17",
            1
        ]
    ],
    "1001309-010": [
        [
            "2016-01-17",
            1
        ]
    ],
    "1001315-001": [
        [
            "2016-01-21",
            1
        ]
    ],
    "1001316-003": [
        [
            "2016-03-01",
            1
        ]
    ],
    "1001316-009": [
        [
            "2016-01-07",
            1
        ]
    ],
    "1001317-002": [
        [
            "2016-07-05",
            1
        ]
    ],
    "1001321-005": [
        [
            "2016-01-29",
            1
        ]
    ],
    "1001325-002": [
        [
            "2016-01-05",
            1
        ]
    ],
    "1001401-016": [
        [
            "2016-02-27",
            1
        ]
    ],
    "1001506-011": [
        [
            "2016-06-03",
            1
        ]
    ],
    "1001601-026": [
        [
            "2016-03-30",
            1
        ]
    ],
    "1001602-022": [
        [
            "2016-01-05",
            1
        ]
    ],
    "1001701-020": [
        [
            "2016-01-24",
            1
        ]
    ],
    "1001706-007": [
        [
            "2016-03-31",
            1
        ]
    ],
    "1001801-016": [
        [
            "2016-04-13",
            1
        ]
    ],
    "1001801-021": [
        [
            "2016-06-09",
            1
        ]
    ],
    "1001802-016": [
        [
            "2016-03-31",
            1
        ]
    ],
    "1001802-022": [
        [
            "2016-02-06",
            1
        ]
    ],
    "1002001-045": [
        [
            "2016-01-14",
            1
        ]
    ],
    "1002002-002": [
        [
            "2016-02-01",
            1
        ]
    ],
    "6300200-033": [
        [
            "2016-06-11",
            1
        ]
    ],
    "6300300-035": [
        [
            "2016-04-16",
            1
        ]
    ],
    "6300300": [
        [
            "2016-01-13",
            1
        ],
        [
            "2016-03-12",
            1
        ]
    ],
    "6300300-022": [
        [
            "2016-04-24",
            1
        ]
    ],
    "6300300-036": [
        [
            "2016-02-26",
            1
        ]
    ],
    "6300300-051": [
        [
            "2016-04-10",
            1
        ]
    ],
    "6300400-004": [
        [
            "2016-06-05",
            1
        ]
    ],
    "6300400-029": [
        [
            "2016-04-01",
            1
        ]
    ],
    "6300500-023": [
        [
            "2016-01-12",
            1
        ]
    ],
    "6300700-002": [
        [
            "2016-05-09",
            1
        ]
    ],
    "6300700-003": [
        [
            "2016-05-31",
            1
        ],
        [
            "2016-07-04",
            1
        ]
    ],
    "6300700-004": [
        [
            "2016-06-08",
            1
        ]
    ],
    "6300800-036": [
        [
            "2016-04-12",
            1
        ]
    ],
    "6301000-005": [
        [
            "2016-01-03",
            1
        ]
    ],
    "6301000-027": [
        [
            "2016-06-07",
            1
        ]
    ],
    "6301100-008": [
        [
            "2016-01-08",
            1
        ]
    ],
    "6301100-013": [
        [
            "2016-03-30",
            1
        ]
    ],
    "6301100-042": [
        [
            "2016-01-26",
            1
        ]
    ],
    "6301200-001": [
        [
            "2016-03-07",
            1
        ]
    ],
    "6301200-012": [
        [
            "2016-04-02",
            1
        ]
    ],
    "6301200-033": [
        [
            "2016-02-12",
            1
        ]
    ],
    "6400100-004": [
        [
            "2016-01-16",
            1
        ]
    ],
    "6400100-008": [
        [
            "2016-01-10",
            1
        ],
        [
            "2016-01-19",
            1
        ]
    ],
    "6400100-011": [
        [
            "2016-01-06",
            1
        ]
    ],
    "6400100-012": [
        [
            "2016-01-02",
            1
        ]
    ],
    "6400100-013": [
        [
            "2016-01-07",
            1
        ],
        [
            "2016-01-08",
            2
        ],
        [
            "2016-01-09",
            1
        ]
    ],
    "6400100-014": [
        [
            "2016-01-06",
            1
        ],
        [
            "2016-01-18",
            1
        ]
    ],
    "6400100-017": [
        [
            "2016-01-02",
            1
        ],
        [
            "2016-01-05",
            1
        ]
    ],
    "6400100-019": [
        [
            "2016-01-26",
            1
        ]
    ],
    "6400200-004": [
        [
            "2016-01-02",
            1
        ],
        [
            "2016-01-03",
            2
        ]
    ],
    "6400200-008": [
        [
            "2016-01-01",
            1
        ],
        [
            "2016-01-12",
            1
        ],
        [
            "2016-01-15",
            1
        ]
    ],
    "6400200-013": [
        [
            "2016-01-04",
            1
        ],
        [
            "2016-01-11",
            1
        ],
        [
            "2016-01-16",
            1
        ],
        [
            "2016-01-18",
            1
        ],
        [
            "2016-01-20",
            1
        ]
    ],
    "6400200-015": [
        [
            "2016-01-01",
            1
        ],
        [
            "2016-01-08",
            1
        ],
        [
            "2016-01-11",
            1
        ],
        [
            "2016-01-13",
            1
        ]
    ],
    "6400200-016": [
        [
            "2016-01-01",
            1
        ],
        [
            "2016-01-04",
            1
        ],
        [
            "2016-01-08",
            1
        ],
        [
            "2016-01-15",
            1
        ],
        [
            "2016-01-20",
            1
        ],
        [
            "2016-02-09",
            1
        ]
    ],
    "6400200-017": [
        [
            "2016-01-12",
            1
        ],
        [
            "2016-01-19",
            1
        ],
        [
            "2016-01-20",
            1
        ],
        [
            "2016-01-28",
            1
        ]
    ],
    "6400200-019": [
        [
            "2016-01-10",
            1
        ]
    ],
    "6400200-020": [
        [
            "2016-01-17",
            1
        ]
    ],
    "6400200-021": [
        [
            "2016-01-02",
            1
        ]
    ],
    "6400200-023": [
        [
            "2016-01-01",
            1
        ]
    ],
    "6400200-026": [
        [
            "2016-01-05",
            1
        ]
    ],
    "6400200-027": [
        [
            "2016-01-06",
            1
        ]
    ],
    "6400200-028": [
        [
            "2016-04-21",
            1
        ]
    ],
    "6400200-032": [
        [
            "2016-01-04",
            1
        ]
    ],
    "6400200-034": [
        [
            "2016-01-02",
            1
        ]
    ],
    "6400200-035": [
        [
            "2016-02-17",
            1
        ]
    ],
    "6400200-038": [
        [
            "2016-01-01",
            1
        ]
    ],
    "6400300-005": [
        [
            "2016-01-11",
            1
        ]
    ],
    "6400300-022": [
        [
            "2016-01-09",
            1
        ]
    ],
    "6400300-026": [
        [
            "2016-01-08",
            1
        ]
    ],
    "6400300-030": [
        [
            "2016-01-04",
            1
        ]
    ],
    "6400300-038": [
        [
            "2016-02-12",
            1
        ]
    ],
    "6400300-039": [
        [
            "2016-01-04",
            1
        ]
    ],
    "6400300-040": [
        [
            "2016-01-06",
            1
        ],
        [
            "2016-02-02",
            1
        ]
    ],
    "6400300-042": [
        [
            "2016-01-06",
            1
        ],
        [
            "2016-01-12",
            1
        ]
    ],
    "6400300-043": [
        [
            "2016-01-01",
            1
        ],
        [
            "2016-01-08",
            1
        ]
    ],
    "6400300-044": [
        [
            "2016-01-08",
            1
        ],
        [
            "2016-01-11",
            1
        ],
        [
            "2016-01-20",
            1
        ]
    ],
    "6400400-001": [
        [
            "2016-01-04",
            1
        ]
    ],
    "6400400-007": [
        [
            "2016-01-19",
            1
        ]
    ],
    "6400400-011": [
        [
            "2016-01-12",
            1
        ]
    ],
    "6400400-014": [
        [
            "2016-01-05",
            1
        ],
        [
            "2016-01-14",
            1
        ]
    ],
    "6400400-022": [
        [
            "2016-06-05",
            1
        ]
    ],
    "6400400-029": [
        [
            "2016-01-13",
            1
        ]
    ],
    "6400400-033": [
        [
            "2016-01-03",
            1
        ]
    ],
    "6400400-034": [
        [
            "2016-01-02",
            1
        ]
    ],
    "6400500-004": [
        [
            "2016-02-24",
            1
        ]
    ],
    "6400500-005": [
        [
            "2016-01-09",
            1
        ],
        [
            "2016-01-11",
            1
        ]
    ],
    "6400500-007": [
        [
            "2016-01-04",
            1
        ],
        [
            "2016-01-06",
            1
        ],
        [
            "2016-01-11",
            1
        ],
        [
            "2016-01-15",
            1
        ]
    ],
    "6400500-008": [
        [
            "2016-01-14",
            1
        ]
    ],
    "6400500-009": [
        [
            "2016-01-01",
            1
        ],
        [
            "2016-02-12",
            1
        ]
    ],
    "6400500-011": [
        [
            "2016-01-03",
            1
        ]
    ],
    "6400500-012": [
        [
            "2016-01-05",
            1
        ],
        [
            "2016-01-08",
            1
        ]
    ],
    "6400500-013": [
        [
            "2016-01-26",
            1
        ]
    ],
    "6400500-015": [
        [
            "2016-01-14",
            1
        ]
    ],
    "6400500-016": [
        [
            "2016-01-11",
            1
        ]
    ],
    "6400500-017": [
        [
            "2016-01-12",
            1
        ]
    ],
    "6400500-018": [
        [
            "2016-01-04",
            1
        ],
        [
            "2016-01-05",
            1
        ]
    ],
    "6400500-020": [
        [
            "2016-01-20",
            1
        ]
    ],
    "6400500-022": [
        [
            "2016-01-05",
            1
        ],
        [
            "2016-01-21",
            1
        ]
    ],
    "6400500-023": [
        [
            "2016-01-30",
            1
        ]
    ],
    "6400500-024": [
        [
            "2016-01-07",
            1
        ]
    ],
    "6400500-025": [
        [
            "2016-01-01",
            1
        ],
        [
            "2016-01-05",
            1
        ],
        [
            "2016-01-20",
            1
        ]
    ],
    "6400500-027": [
        [
            "2016-01-02",
            1
        ],
        [
            "2016-01-03",
            1
        ],
        [
            "2016-01-04",
            1
        ]
    ],
    "6400500-028": [
        [
            "2016-01-11",
            1
        ]
    ],
    "6400500-030": [
        [
            "2016-01-21",
            1
        ],
        [
            "2016-02-03",
            1
        ]
    ],
    "6400500-031": [
        [
            "2016-01-03",
            1
        ]
    ],
    "6400500-033": [
        [
            "2016-01-04",
            1
        ],
        [
            "2016-01-05",
            1
        ],
        [
            "2016-01-08",
            1
        ]
    ],
    "6400500-034": [
        [
            "2016-01-26",
            1
        ]
    ],
    "6400500-036": [
        [
            "2016-02-02",
            1
        ]
    ],
    "6400500-038": [
        [
            "2016-01-03",
            1
        ],
        [
            "2016-01-16",
            1
        ]
    ],
    "6400500-039": [
        [
            "2016-01-11",
            1
        ],
        [
            "2016-01-14",
            1
        ]
    ],
    "6400500-040": [
        [
            "2016-01-17",
            1
        ]
    ],
    "6400500-042": [
        [
            "2016-02-01",
            1
        ]
    ],
    "6400500-044": [
        [
            "2016-01-08",
            1
        ],
        [
            "2016-01-11",
            1
        ],
        [
            "2016-01-21",
            1
        ]
    ],
    "6400500-045": [
        [
            "2016-01-06",
            1
        ]
    ],
    "6400500-049": [
        [
            "2016-01-04",
            1
        ],
        [
            "2016-01-13",
            1
        ]
    ],
    "6400500-050": [
        [
            "2016-01-22",
            1
        ]
    ],
    "6400500-051": [
        [
            "2016-01-04",
            1
        ]
    ],
    "6400500-052": [
        [
            "2016-01-04",
            1
        ]
    ],
    "6400500-053": [
        [
            "2016-01-05",
            1
        ],
        [
            "2016-01-18",
            1
        ]
    ],
    "6400500-054": [
        [
            "2016-01-07",
            1
        ]
    ],
    "6400500-055": [
        [
            "2016-01-02",
            1
        ],
        [
            "2016-01-08",
            1
        ]
    ],
    "6400500-059": [
        [
            "2016-01-08",
            1
        ]
    ],
    "6400500-060": [
        [
            "2016-01-04",
            1
        ]
    ],
    "6400500-061": [
        [
            "2016-01-28",
            1
        ]
    ],
    "6400500-063": [
        [
            "2016-01-05",
            1
        ],
        [
            "2016-01-06",
            1
        ],
        [
            "2016-01-08",
            1
        ]
    ],
    "6400500-064": [
        [
            "2016-01-28",
            1
        ]
    ],
    "6400500-069": [
        [
            "2016-01-02",
            1
        ]
    ],
    "6400500-085": [
        [
            "2016-01-19",
            1
        ]
    ],
    "6400500-088": [
        [
            "2016-01-03",
            1
        ]
    ],
    "6400600-004": [
        [
            "2016-01-27",
            1
        ]
    ],
    "6400600-007": [
        [
            "2016-01-15",
            1
        ]
    ],
    "6400600-008": [
        [
            "2016-01-04",
            1
        ]
    ],
    "6400600-013": [
        [
            "2016-01-17",
            1
        ]
    ],
    "6400600-014": [
        [
            "2016-01-04",
            1
        ]
    ],
    "6400600-019": [
        [
            "2016-01-01",
            1
        ],
        [
            "2016-01-12",
            1
        ]
    ],
    "6400600-020": [
        [
            "2016-01-08",
            1
        ],
        [
            "2016-02-04",
            1
        ]
    ],
    "6400600-021": [
        [
            "2016-01-15",
            1
        ]
    ],
    "6400600-022": [
        [
            "2016-01-04",
            1
        ]
    ],
    "6400600-029": [
        [
            "2016-01-14",
            1
        ]
    ],
    "6400700-003": [
        [
            "2016-01-08",
            1
        ],
        [
            "2016-01-16",
            1
        ]
    ],
    "6400700-004": [
        [
            "2016-01-12",
            1
        ]
    ],
    "6400700-015": [
        [
            "2016-01-07",
            1
        ]
    ],
    "6400700-019": [
        [
            "2016-01-09",
            1
        ]
    ],
    "6400800-002": [
        [
            "2016-01-06",
            1
        ]
    ],
    "6400800-003": [
        [
            "2016-02-02",
            1
        ]
    ],
    "6400800-013": [
        [
            "2016-01-21",
            1
        ]
    ],
    "6400800-015": [
        [
            "2016-01-04",
            3
        ],
        [
            "2016-01-09",
            1
        ],
        [
            "2016-01-11",
            1
        ]
    ],
    "6400800-016": [
        [
            "2016-01-05",
            1
        ]
    ],
    "6400800-017": [
        [
            "2016-01-02",
            1
        ],
        [
            "2016-01-04",
            1
        ],
        [
            "2016-01-11",
            1
        ],
        [
            "2016-01-12",
            1
        ]
    ],
    "6400800-018": [
        [
            "2016-01-05",
            1
        ]
    ],
    "6400800-019": [
        [
            "2016-01-02",
            1
        ],
        [
            "2016-01-21",
            1
        ]
    ],
    "6400800-029": [
        [
            "2016-01-05",
            1
        ]
    ],
    "6400800-031": [
        [
            "2016-01-04",
            1
        ]
    ],
    "6400800-032": [
        [
            "2016-01-04",
            1
        ]
    ],
    "6400800-037": [
        [
            "2016-01-14",
            1
        ],
        [
            "2016-01-21",
            1
        ]
    ],
    "6400800-038": [
        [
            "2016-01-01",
            1
        ]
    ],
    "6400800-039": [
        [
            "2016-01-05",
            1
        ],
        [
            "2016-01-06",
            1
        ]
    ],
    "6400800-045": [
        [
            "2016-01-02",
            1
        ],
        [
            "2016-01-07",
            1
        ]
    ],
    "6400800-046": [
        [
            "2016-01-05",
            1
        ]
    ],
    "6400800-047": [
        [
            "2016-01-01",
            1
        ]
    ],
    "6400800-048": [
        [
            "2016-01-05",
            1
        ]
    ],
    "6400800-049": [
        [
            "2016-01-04",
            1
        ],
        [
            "2016-01-07",
            1
        ]
    ],
    "6400800-050": [
        [
            "2016-01-08",
            1
        ]
    ],
    "6400800-051": [
        [
            "2016-01-05",
            1
        ],
        [
            "2016-01-07",
            2
        ]
    ],
    "6400800-054": [
        [
            "2016-01-01",
            1
        ]
    ],
    "6400800-055": [
        [
            "2016-01-13",
            1
        ],
        [
            "2016-01-25",
            1
        ]
    ],
    "6400800-056": [
        [
            "2016-01-08",
            1
        ],
        [
            "2016-01-27",
            1
        ],
        [
            "2016-02-03",
            1
        ]
    ],
    "6400800-057": [
        [
            "2016-01-02",
            1
        ],
        [
            "2016-01-11",
            1
        ]
    ],
    "6400800-060": [
        [
            "2016-01-01",
            1
        ],
        [
            "2016-01-05",
            1
        ]
    ],
    "6400800-061": [
        [
            "2016-01-16",
            1
        ],
        [
            "2016-01-22",
            1
        ]
    ],
    "6400800-062": [
        [
            "2016-01-07",
            1
        ]
    ],
    "6400800-063": [
        [
            "2016-01-05",
            1
        ]
    ],
    "6400800-067": [
        [
            "2016-02-15",
            1
        ]
    ],
    "6400800-068": [
        [
            "2016-01-25",
            1
        ]
    ],
    "6400800-069": [
        [
            "2016-01-03",
            1
        ]
    ],
    "6400900-001": [
        [
            "2016-01-04",
            2
        ],
        [
            "2016-01-08",
            1
        ],
        [
            "2016-01-20",
            1
        ]
    ],
    "6400900-002": [
        [
            "2016-01-03",
            1
        ]
    ],
    "6400900-003": [
        [
            "2016-01-03",
            1
        ],
        [
            "2016-01-13",
            1
        ]
    ],
    "6400900-005": [
        [
            "2016-01-08",
            1
        ],
        [
            "2016-01-19",
            1
        ]
    ],
    "6400900-008": [
        [
            "2016-01-02",
            1
        ],
        [
            "2016-01-20",
            1
        ],
        [
            "2016-01-22",
            1
        ]
    ],
    "6400900-011": [
        [
            "2016-03-07",
            1
        ]
    ],
    "6400900-015": [
        [
            "2016-02-17",
            1
        ]
    ],
    "6400900-017": [
        [
            "2016-01-01",
            1
        ],
        [
            "2016-01-06",
            1
        ]
    ],
    "6400900-019": [
        [
            "2016-01-04",
            1
        ]
    ],
    "6400900-023": [
        [
            "2016-01-05",
            1
        ]
    ],
    "6400900-024": [
        [
            "2016-01-04",
            1
        ],
        [
            "2016-01-17",
            1
        ]
    ],
    "6400900-030": [
        [
            "2016-01-11",
            1
        ]
    ],
    "6400900-035": [
        [
            "2016-01-15",
            1
        ]
    ],
    "6400900-036": [
        [
            "2016-01-01",
            1
        ]
    ],
    "6400900-037": [
        [
            "2016-01-13",
            2
        ],
        [
            "2016-01-21",
            1
        ]
    ],
    "6400900-039": [
        [
            "2016-01-02",
            1
        ],
        [
            "2016-01-09",
            1
        ]
    ],
    "6400900-040": [
        [
            "2016-01-07",
            1
        ]
    ],
    "6400900-041": [
        [
            "2016-01-05",
            1
        ]
    ],
    "6400900-042": [
        [
            "2016-01-02",
            1
        ],
        [
            "2016-01-04",
            1
        ],
        [
            "2016-01-05",
            1
        ],
        [
            "2016-01-11",
            1
        ],
        [
            "2016-01-14",
            1
        ]
    ],
    "6400900-043": [
        [
            "2016-01-06",
            1
        ],
        [
            "2016-01-18",
            1
        ]
    ],
    "6400900-044": [
        [
            "2016-01-03",
            1
        ],
        [
            "2016-01-13",
            1
        ]
    ],
    "6400900-047": [
        [
            "2016-01-01",
            1
        ]
    ],
    "6400900-049": [
        [
            "2016-01-02",
            1
        ],
        [
            "2016-01-04",
            3
        ],
        [
            "2016-01-20",
            1
        ]
    ],
    "6400900-055": [
        [
            "2016-01-05",
            1
        ]
    ],
    "6400900-059": [
        [
            "2016-02-04",
            1
        ]
    ],
    "6400900-060": [
        [
            "2016-01-01",
            1
        ],
        [
            "2016-01-18",
            1
        ],
        [
            "2016-01-19",
            1
        ]
    ],
    "6401000-004": [
        [
            "2016-01-04",
            1
        ]
    ],
    "6401000-005": [
        [
            "2016-01-05",
            1
        ]
    ],
    "6401000-006": [
        [
            "2016-01-04",
            1
        ],
        [
            "2016-01-07",
            1
        ]
    ],
    "6401000-010": [
        [
            "2016-01-14",
            1
        ]
    ],
    "6401100-002": [
        [
            "2016-01-02",
            1
        ]
    ],
    "6401100-003": [
        [
            "2016-01-11",
            2
        ],
        [
            "2016-01-12",
            1
        ],
        [
            "2016-01-13",
            1
        ]
    ],
    "6401100-004": [
        [
            "2016-01-01",
            2
        ]
    ],
    "6401100-006": [
        [
            "2016-01-15",
            1
        ]
    ],
    "6401100-009": [
        [
            "2016-01-15",
            1
        ]
    ],
    "6401100-010": [
        [
            "2016-01-14",
            1
        ],
        [
            "2016-01-18",
            1
        ]
    ],
    "6401100-013": [
        [
            "2016-01-14",
            1
        ]
    ],
    "6401100-014": [
        [
            "2016-01-04",
            1
        ]
    ],
    "6401100-015": [
        [
            "2016-01-14",
            1
        ]
    ],
    "6401100-016": [
        [
            "2016-01-11",
            1
        ]
    ],
    "6401100-018": [
        [
            "2016-01-05",
            1
        ],
        [
            "2016-01-15",
            1
        ],
        [
            "2016-01-19",
            1
        ]
    ],
    "6401100-020": [
        [
            "2016-01-07",
            1
        ],
        [
            "2016-01-10",
            1
        ]
    ],
    "6401100-021": [
        [
            "2016-01-04",
            1
        ]
    ],
    "6401100-022": [
        [
            "2016-01-04",
            1
        ],
        [
            "2016-01-07",
            1
        ],
        [
            "2016-07-01",
            1
        ]
    ],
    "6401100-024": [
        [
            "2016-01-31",
            1
        ]
    ],
    "6401100-029": [
        [
            "2016-01-15",
            1
        ],
        [
            "2016-02-02",
            1
        ],
        [
            "2016-02-05",
            1
        ]
    ],
    "6401100-030": [
        [
            "2016-01-14",
            1
        ]
    ],
    "6401100-031": [
        [
            "2016-01-12",
            1
        ],
        [
            "2016-01-13",
            1
        ]
    ],
    "6401100-032": [
        [
            "2016-01-02",
            1
        ]
    ],
    "6401200-006": [
        [
            "2016-01-11",
            1
        ]
    ],
    "6401200-007": [
        [
            "2016-01-18",
            1
        ]
    ],
    "6401200-010": [
        [
            "2016-01-07",
            1
        ]
    ],
    "6401200-011": [
        [
            "2016-01-01",
            1
        ]
    ],
    "6401200-012": [
        [
            "2016-01-03",
            1
        ],
        [
            "2016-01-12",
            1
        ],
        [
            "2016-01-13",
            1
        ]
    ],
    "6401200-015": [
        [
            "2016-01-06",
            1
        ]
    ],
    "6401200-017": [
        [
            "2016-01-02",
            1
        ],
        [
            "2016-01-21",
            1
        ],
        [
            "2016-01-30",
            1
        ]
    ],
    "6401200-019": [
        [
            "2016-01-03",
            1
        ],
        [
            "2016-01-10",
            1
        ]
    ],
    "6401200-020": [
        [
            "2016-01-13",
            1
        ]
    ],
    "6401200-024": [
        [
            "2016-01-02",
            1
        ]
    ],
    "6401200-026": [
        [
            "2016-01-12",
            1
        ]
    ],
    "6401200-027": [
        [
            "2016-01-05",
            1
        ]
    ],
    "6401200-029": [
        [
            "2016-01-11",
            1
        ]
    ],
    "6401200-030": [
        [
            "2016-01-15",
            1
        ]
    ],
    "6401200-033": [
        [
            "2016-01-29",
            1
        ]
    ],
    "6401200-034": [
        [
            "2016-01-06",
            1
        ]
    ],
    "6401200-035": [
        [
            "2016-01-17",
            1
        ]
    ],
    "6401200-038": [
        [
            "2016-01-05",
            1
        ],
        [
            "2016-01-12",
            1
        ]
    ],
    "6401200-039": [
        [
            "2016-01-07",
            1
        ],
        [
            "2016-01-18",
            1
        ]
    ],
    "6401200-040": [
        [
            "2016-01-04",
            2
        ],
        [
            "2016-01-05",
            1
        ],
        [
            "2016-01-06",
            1
        ]
    ],
    "6401200-042": [
        [
            "2016-01-13",
            1
        ]
    ],
    "6401200-043": [
        [
            "2016-01-04",
            1
        ],
        [
            "2016-01-25",
            1
        ]
    ],
    "6401200-046": [
        [
            "2016-01-17",
            1
        ]
    ],
    "6401200-047": [
        [
            "2016-01-04",
            1
        ],
        [
            "2016-01-11",
            1
        ]
    ],
    "6401200-048": [
        [
            "2016-01-02",
            1
        ]
    ],
    "6401200-049": [
        [
            "2016-01-02",
            1
        ]
    ],
    "6401200-050": [
        [
            "2016-01-02",
            1
        ],
        [
            "2016-01-14",
            1
        ],
        [
            "2016-01-18",
            2
        ]
    ],
    "6401200-051": [
        [
            "2016-01-22",
            2
        ]
    ],
    "6401200-053": [
        [
            "2016-01-05",
            1
        ]
    ],
    "6401200-055": [
        [
            "2016-01-04",
            1
        ]
    ],
    "6401200-056": [
        [
            "2016-01-04",
            1
        ],
        [
            "2016-01-11",
            1
        ]
    ],
    "6401200-057": [
        [
            "2016-01-08",
            1
        ]
    ],
    "6401200-058": [
        [
            "2016-01-15",
            1
        ]
    ],
    "6401200-059": [
        [
            "2016-01-01",
            1
        ],
        [
            "2016-01-04",
            1
        ]
    ],
    "6401200-060": [
        [
            "2016-01-09",
            1
        ]
    ],
    "6401200-061": [
        [
            "2016-01-06",
            1
        ]
    ],
    "6401200-062": [
        [
            "2016-01-20",
            1
        ],
        [
            "2016-04-19",
            1
        ]
    ],
    "6401200-063": [
        [
            "2016-01-12",
            1
        ],
        [
            "2016-01-16",
            1
        ]
    ],
    "6401200-064": [
        [
            "2016-01-16",
            1
        ]
    ],
    "6401200-066": [
        [
            "2016-01-04",
            1
        ]
    ],
    "6401200-072": [
        [
            "2016-01-04",
            2
        ],
        [
            "2016-01-07",
            1
        ],
        [
            "2016-01-10",
            1
        ]
    ],
    "6401200-074": [
        [
            "2016-01-23",
            1
        ]
    ],
    "6401200-075": [
        [
            "2016-01-01",
            1
        ]
    ],
    "6401200-076": [
        [
            "2016-01-19",
            1
        ]
    ],
    "6401200-077": [
        [
            "2016-01-02",
            1
        ],
        [
            "2016-01-10",
            1
        ]
    ],
    "6401200-078": [
        [
            "2016-01-04",
            1
        ]
    ],
    "6401300-004": [
        [
            "2016-02-04",
            1
        ]
    ],
    "6401300-009": [
        [
            "2016-01-18",
            1
        ],
        [
            "2016-01-30",
            1
        ]
    ],
    "6401300-020": [
        [
            "2016-02-01",
            1
        ]
    ],
    "6401300-023": [
        [
            "2016-01-06",
            1
        ]
    ],
    "6401400-001": [
        [
            "2016-01-03",
            1
        ]
    ],
    "6401400-002": [
        [
            "2016-01-10",
            1
        ]
    ],
    "6401400-003": [
        [
            "2016-01-04",
            1
        ],
        [
            "2016-01-18",
            1
        ]
    ],
    "6401400-007": [
        [
            "2016-01-20",
            1
        ],
        [
            "2016-01-26",
            1
        ]
    ],
    "6401400-008": [
        [
            "2016-01-12",
            1
        ],
        [
            "2016-01-18",
            1
        ]
    ],
    "6401400-009": [
        [
            "2016-01-04",
            1
        ],
        [
            "2016-01-05",
            1
        ],
        [
            "2016-01-13",
            1
        ],
        [
            "2016-01-16",
            1
        ],
        [
            "2016-01-20",
            1
        ],
        [
            "2016-01-29",
            1
        ],
        [
            "2016-01-31",
            1
        ],
        [
            "2016-02-05",
            1
        ]
    ],
    "6401400-015": [
        [
            "2016-01-04",
            1
        ]
    ],
    "6401400-016": [
        [
            "2016-01-13",
            1
        ]
    ],
    "6401400-017": [
        [
            "2016-01-20",
            1
        ]
    ],
    "6401400-021": [
        [
            "2016-04-28",
            1
        ]
    ],
    "6401400-025": [
        [
            "2016-01-01",
            2
        ],
        [
            "2016-01-06",
            1
        ],
        [
            "2016-01-07",
            1
        ],
        [
            "2016-01-10",
            1
        ],
        [
            "2016-01-12",
            1
        ],
        [
            "2016-01-17",
            1
        ],
        [
            "2016-01-19",
            2
        ]
    ],
    "6401500-002": [
        [
            "2016-01-18",
            1
        ]
    ],
    "6401500-006": [
        [
            "2016-01-29",
            1
        ]
    ],
    "6401600-001": [
        [
            "2016-02-01",
            1
        ]
    ],
    "6401600-005": [
        [
            "2016-01-04",
            1
        ]
    ],
    "6401600-006": [
        [
            "2016-01-04",
            1
        ],
        [
            "2016-05-02",
            1
        ]
    ],
    "6401600-008": [
        [
            "2016-01-04",
            1
        ]
    ],
    "6401700-002": [
        [
            "2016-01-20",
            1
        ]
    ],
    "6401700-007": [
        [
            "2016-01-04",
            2
        ],
        [
            "2016-01-13",
            1
        ]
    ],
    "6401700-009": [
        [
            "2016-01-06",
            1
        ],
        [
            "2016-02-06",
            1
        ]
    ],
    "6401700-012": [
        [
            "2016-01-05",
            1
        ],
        [
            "2016-01-11",
            1
        ],
        [
            "2016-01-13",
            1
        ],
        [
            "2016-01-18",
            1
        ]
    ],
    "6401700-013": [
        [
            "2016-01-03",
            1
        ],
        [
            "2016-01-04",
            1
        ]
    ],
    "6401700-015": [
        [
            "2016-01-02",
            1
        ]
    ],
    "6401800-001": [
        [
            "2016-04-05",
            1
        ]
    ],
    "6401800-003": [
        [
            "2016-01-04",
            1
        ]
    ],
    "6401900-003": [
        [
            "2016-01-04",
            1
        ],
        [
            "2016-01-05",
            1
        ]
    ],
    "6401900-010": [
        [
            "2016-01-20",
            1
        ]
    ],
    "6401900-012": [
        [
            "2016-01-07",
            1
        ]
    ],
    "6401900-019": [
        [
            "2016-01-08",
            2
        ]
    ],
    "6402000-007": [
        [
            "2016-01-09",
            1
        ]
    ],
    "6402000-013": [
        [
            "2016-01-08",
            1
        ]
    ],
    "6402100-008": [
        [
            "2016-01-19",
            1
        ]
    ],
    "6402100-011": [
        [
            "2016-01-20",
            1
        ]
    ],
    "6402300-012": [
        [
            "2016-01-04",
            1
        ]
    ],
    "6402400-012": [
        [
            "2016-01-11",
            1
        ]
    ],
    "6402400-015": [
        [
            "2016-01-27",
            1
        ]
    ],
    "6402600-007": [
        [
            "2016-01-30",
            1
        ]
    ],
    "6403000-003": [
        [
            "2016-01-04",
            1
        ],
        [
            "2016-01-13",
            1
        ]
    ],
    "6403000-015": [
        [
            "2016-01-08",
            1
        ],
        [
            "2016-01-09",
            1
        ]
    ],
    "6403000-020": [
        [
            "2016-02-04",
            1
        ]
    ],
    "6403100-003": [
        [
            "2016-01-07",
            1
        ]
    ],
    "6403800-001": [
        [
            "2016-01-04",
            1
        ]
    ],
    "6500100-021": [
        [
            "2016-04-20",
            1
        ]
    ],
    "6500100-022": [
        [
            "2016-05-07",
            1
        ]
    ],
    "6500100-045": [
        [
            "2016-06-08",
            1
        ]
    ],
    "6500100-052": [
        [
            "2016-02-19",
            1
        ]
    ],
    "6500100-089": [
        [
            "2016-02-19",
            1
        ]
    ],
    "6500100-124": [
        [
            "2016-05-02",
            1
        ]
    ],
    "6500200-083": [
        [
            "2016-03-21",
            1
        ]
    ],
    "6500300-022": [
        [
            "2016-06-16",
            1
        ]
    ],
    "6500300-027": [
        [
            "2016-01-04",
            1
        ]
    ],
    "6500300": [
        [
            "2016-05-19",
            1
        ]
    ],
    "6500300-051": [
        [
            "2016-04-11",
            1
        ]
    ],
    "6500400-052": [
        [
            "2016-01-07",
            1
        ]
    ],
    "6500500-008": [
        [
            "2016-02-12",
            1
        ]
    ],
    "6500500-019": [
        [
            "2016-01-27",
            1
        ]
    ],
    "6500500-064": [
        [
            "2016-04-15",
            1
        ]
    ],
    "6500700-031": [
        [
            "2016-02-07",
            1
        ]
    ],
    "6500900-024": [
        [
            "2016-05-30",
            1
        ]
    ],
    "6501000-020": [
        [
            "2016-01-16",
            1
        ],
        [
            "2016-04-24",
            1
        ]
    ],
    "6501400-001": [
        [
            "2016-03-11",
            1
        ]
    ],
    "6501700-015": [
        [
            "2016-02-05",
            1
        ]
    ],
    "6501800-002": [
        [
            "2016-03-01",
            1
        ]
    ],
    "6600400-002": [
        [
            "2016-05-24",
            1
        ]
    ],
    "6600400-007": [
        [
            "2016-03-26",
            1
        ]
    ],
    "6600400": [
        [
            "2016-02-13",
            1
        ],
        [
            "2016-02-15",
            1
        ]
    ],
    "6600500-009": [
        [
            "2016-06-21",
            1
        ]
    ],
    "6600500-032": [
        [
            "2016-06-06",
            1
        ]
    ],
    "6600500-036": [
        [
            "2016-04-06",
            1
        ]
    ],
    "6600600-010": [
        [
            "2016-04-21",
            1
        ]
    ],
    "6600600-019": [
        [
            "2016-05-25",
            1
        ]
    ],
    "6600600-039": [
        [
            "2016-02-05",
            1
        ]
    ],
    "6600700-007": [
        [
            "2016-02-15",
            1
        ]
    ],
    "6600800-008": [
        [
            "2016-06-13",
            1
        ]
    ],
    "6600800-013": [
        [
            "2016-01-26",
            1
        ]
    ],
    "6601100-006": [
        [
            "2016-05-28",
            1
        ]
    ],
    "6601100-007": [
        [
            "2016-01-28",
            1
        ]
    ],
    "6601100-013": [
        [
            "2016-01-03",
            1
        ]
    ],
    "6601200-014": [
        [
            "2016-06-20",
            1
        ]
    ],
    "6601300-008": [
        [
            "2016-05-20",
            1
        ]
    ],
    "6601300-011": [
        [
            "2016-01-04",
            1
        ]
    ],
    "6601400-007": [
        [
            "2016-03-24",
            1
        ]
    ],
    "6601600": [
        [
            "2016-02-01",
            1
        ]
    ],
    "6602300": [
        [
            "2016-07-07",
            1
        ]
    ],
    "6602700-020": [
        [
            "2016-03-15",
            1
        ]
    ],
    "6700800-005": [
        [
            "2016-06-30",
            1
        ]
    ],
    "6701000-002": [
        [
            "2016-05-19",
            1
        ]
    ],
    "6701500-012": [
        [
            "2016-01-02",
            1
        ]
    ],
    "6701500-013": [
        [
            "2016-06-27",
            1
        ]
    ],
    "6702700-008": [
        [
            "2016-01-04",
            1
        ]
    ],
    "6702800-003": [
        [
            "2016-01-01",
            2
        ]
    ],
    "6702800-012": [
        [
            "2016-01-25",
            1
        ]
    ],
    "6703000-007": [
        [
            "2016-01-20",
            1
        ]
    ],
    "6703100-029": [
        [
            "2016-01-04",
            1
        ],
        [
            "2016-01-08",
            1
        ]
    ],
    "6703200-008": [
        [
            "2016-06-23",
            1
        ]
    ],
    "6703200-038": [
        [
            "2016-01-06",
            1
        ]
    ],
    "6703200-041": [
        [
            "2016-02-27",
            1
        ]
    ],
    "6703300-005": [
        [
            "2016-01-05",
            1
        ]
    ],
    "6703400-030": [
        [
            "2016-01-13",
            1
        ]
    ],
    "6703400-038": [
        [
            "2016-01-14",
            1
        ]
    ],
    "6703500-041": [
        [
            "2016-03-21",
            1
        ]
    ],
    "6703500-043": [
        [
            "2016-03-08",
            1
        ]
    ],
    "6703500-046": [
        [
            "2016-01-01",
            1
        ]
    ],
    "6703600-008": [
        [
            "2016-03-04",
            1
        ]
    ],
    "6703600-012": [
        [
            "2016-01-12",
            1
        ]
    ],
    "6703700-005": [
        [
            "2016-02-13",
            1
        ]
    ],
    "6800100-026": [
        [
            "2016-05-05",
            1
        ]
    ],
    "6800100-032": [
        [
            "2016-02-22",
            1
        ]
    ],
    "6800100-046": [
        [
            "2016-06-04",
            1
        ]
    ],
    "6800100-049": [
        [
            "2016-05-14",
            1
        ]
    ],
    "6800100-059": [
        [
            "2016-02-04",
            1
        ]
    ],
    "6800100-072": [
        [
            "2016-06-04",
            1
        ]
    ],
    "6800200-022": [
        [
            "2016-02-05",
            1
        ]
    ],
    "6800200-031": [
        [
            "2016-03-25",
            1
        ]
    ],
    "6800200-051": [
        [
            "2016-03-01",
            1
        ]
    ],
    "6800200-056": [
        [
            "2016-04-17",
            1
        ]
    ],
    "6800400-010": [
        [
            "2016-01-29",
            1
        ]
    ],
    "6800400-021": [
        [
            "2016-05-12",
            1
        ]
    ],
    "6800500-016": [
        [
            "2016-05-16",
            1
        ]
    ],
    "6800500-018": [
        [
            "2016-02-15",
            1
        ]
    ],
    "6800500-020": [
        [
            "2016-05-08",
            1
        ]
    ],
    "6800600-007": [
        [
            "2016-01-01",
            1
        ]
    ],
    "6800600-010": [
        [
            "2016-02-12",
            1
        ]
    ],
    "6800700-004": [
        [
            "2016-03-05",
            1
        ]
    ],
    "6800700-012": [
        [
            "2016-01-30",
            1
        ]
    ],
    "6800700-013": [
        [
            "2016-01-19",
            1
        ]
    ],
    "6800700-027": [
        [
            "2016-04-22",
            1
        ],
        [
            "2016-06-27",
            1
        ]
    ],
    "6800800-006": [
        [
            "2016-02-11",
            1
        ]
    ],
    "6800800-013": [
        [
            "2016-06-22",
            1
        ]
    ],
    "6801000-016": [
        [
            "2016-02-15",
            1
        ]
    ],
    "6801200-022": [
        [
            "2016-01-01",
            1
        ]
    ],
    "total": [
        [
            "2016-01-01",
            30
        ],
        [
            "2016-01-02",
            27
        ],
        [
            "2016-01-03",
            19
        ],
        [
            "2016-01-04",
            66
        ],
        [
            "2016-01-05",
            36
        ],
        [
            "2016-01-06",
            20
        ],
        [
            "2016-01-07",
            21
        ],
        [
            "2016-01-08",
            26
        ],
        [
            "2016-01-09",
            9
        ],
        [
            "2016-01-10",
            8
        ],
        [
            "2016-01-11",
            26
        ],
        [
            "2016-01-12",
            19
        ],
        [
            "2016-01-13",
            22
        ],
        [
            "2016-01-14",
            15
        ],
        [
            "2016-01-15",
            13
        ],
        [
            "2016-01-16",
            11
        ],
        [
            "2016-01-17",
            9
        ],
        [
            "2016-01-18",
            16
        ],
        [
            "2016-01-19",
            12
        ],
        [
            "2016-01-20",
            17
        ],
        [
            "2016-01-21",
            9
        ],
        [
            "2016-01-22",
            7
        ],
        [
            "2016-01-23",
            1
        ],
        [
            "2016-01-24",
            1
        ],
        [
            "2016-01-25",
            7
        ],
        [
            "2016-01-26",
            6
        ],
        [
            "2016-01-27",
            4
        ],
        [
            "2016-01-28",
            4
        ],
        [
            "2016-01-29",
            6
        ],
        [
            "2016-01-30",
            6
        ],
        [
            "2016-01-31",
            2
        ],
        [
            "2016-02-01",
            5
        ],
        [
            "2016-02-02",
            4
        ],
        [
            "2016-02-03",
            3
        ],
        [
            "2016-02-04",
            6
        ],
        [
            "2016-02-05",
            5
        ],
        [
            "2016-02-06",
            2
        ],
        [
            "2016-02-07",
            1
        ],
        [
            "2016-02-09",
            1
        ],
        [
            "2016-02-11",
            1
        ],
        [
            "2016-02-12",
            5
        ],
        [
            "2016-02-13",
            3
        ],
        [
            "2016-02-14",
            1
        ],
        [
            "2016-02-15",
            6
        ],
        [
            "2016-02-17",
            2
        ],
        [
            "2016-02-19",
            2
        ],
        [
            "2016-02-22",
            1
        ],
        [
            "2016-02-24",
            1
        ],
        [
            "2016-02-26",
            1
        ],
        [
            "2016-02-27",
            2
        ],
        [
            "2016-03-01",
            3
        ],
        [
            "2016-03-04",
            1
        ],
        [
            "2016-03-05",
            1
        ],
        [
            "2016-03-07",
            2
        ],
        [
            "2016-03-08",
            1
        ],
        [
            "2016-03-11",
            1
        ],
        [
            "2016-03-12",
            1
        ],
        [
            "2016-03-15",
            1
        ],
        [
            "2016-03-21",
            2
        ],
        [
            "2016-03-24",
            1
        ],
        [
            "2016-03-25",
            1
        ],
        [
            "2016-03-26",
            1
        ],
        [
            "2016-03-30",
            2
        ],
        [
            "2016-03-31",
            2
        ],
        [
            "2016-04-01",
            1
        ],
        [
            "2016-04-02",
            1
        ],
        [
            "2016-04-05",
            1
        ],
        [
            "2016-04-06",
            1
        ],
        [
            "2016-04-10",
            2
        ],
        [
            "2016-04-11",
            1
        ],
        [
            "2016-04-12",
            1
        ],
        [
            "2016-04-13",
            1
        ],
        [
            "2016-04-15",
            1
        ],
        [
            "2016-04-16",
            1
        ],
        [
            "2016-04-17",
            1
        ],
        [
            "2016-04-19",
            1
        ],
        [
            "2016-04-20",
            2
        ],
        [
            "2016-04-21",
            2
        ],
        [
            "2016-04-22",
            2
        ],
        [
            "2016-04-24",
            2
        ],
        [
            "2016-04-28",
            1
        ],
        [
            "2016-05-02",
            2
        ],
        [
            "2016-05-03",
            1
        ],
        [
            "2016-05-05",
            1
        ],
        [
            "2016-05-07",
            1
        ],
        [
            "2016-05-08",
            1
        ],
        [
            "2016-05-09",
            1
        ],
        [
            "2016-05-12",
            1
        ],
        [
            "2016-05-14",
            1
        ],
        [
            "2016-05-15",
            1
        ],
        [
            "2016-05-16",
            1
        ],
        [
            "2016-05-17",
            1
        ],
        [
            "2016-05-18",
            1
        ],
        [
            "2016-05-19",
            2
        ],
        [
            "2016-05-20",
            1
        ],
        [
            "2016-05-24",
            1
        ],
        [
            "2016-05-25",
            2
        ],
        [
            "2016-05-28",
            1
        ],
        [
            "2016-05-30",
            1
        ],
        [
            "2016-05-31",
            1
        ],
        [
            "2016-06-01",
            1
        ],
        [
            "2016-06-03",
            1
        ],
        [
            "2016-06-04",
            2
        ],
        [
            "2016-06-05",
            3
        ],
        [
            "2016-06-06",
            1
        ],
        [
            "2016-06-07",
            1
        ],
        [
            "2016-06-08",
            2
        ],
        [
            "2016-06-09",
            1
        ],
        [
            "2016-06-11",
            1
        ],
        [
            "2016-06-13",
            1
        ],
        [
            "2016-06-16",
            2
        ],
        [
            "2016-06-20",
            1
        ],
        [
            "2016-06-21",
            1
        ],
        [
            "2016-06-22",
            1
        ],
        [
            "2016-06-23",
            1
        ],
        [
            "2016-06-25",
            1
        ],
        [
            "2016-06-26",
            1
        ],
        [
            "2016-06-27",
            2
        ],
        [
            "2016-06-30",
            1
        ],
        [
            "2016-07-01",
            1
        ],
        [
            "2016-07-04",
            1
        ],
        [
            "2016-07-05",
            1
        ],
        [
            "2016-07-06",
            1
        ],
        [
            "2016-07-07",
            1
        ]
    ]
}